<?xml version="1.0"?>

<PropertyList>

<path>dhc8-400.ac</path> 

<offsets>
<z-m>0</z-m>
<pitch-deg>0</pitch-deg>
</offsets>
<nasal>
<load>
var livery_update = aircraft.livery_update.new("Aircraft/Q400/Models/Liveries");
</load>

<unload>
livery_update.stop();
</unload>
</nasal>


<animation>
      <type>material</type>
	<object-name>wingroot</object-name>
      <object-name>LLG.door</object-name>
      <object-name>RLG.door</object-name>
      <object-name>Lwing</object-name>
      <object-name>Lfuselage</object-name>
      <object-name>Rfuselage</object-name>
      <object-name>rudder</object-name>
      <object-name>Elevator</object-name>
      <object-name>tail</object-name>
	<object-name>R.aileron</object-name>
	<object-name>L.aileron</object-name>
	<object-name>Rwing</object-name>
	<object-name>R.flap</object-name>
	<object-name>L.flap</object-name>
	<object-name>ball</object-name>
	<object-name>cabindoor</object-name>
      <property-base>sim/model/livery</property-base>
      <texture-prop>texture</texture-prop>
      <texture>AVA.png</texture>

    </animation>
<animation>

<type>material</type>
<object-name>Lengine</object-name>
<object-name>Rengine</object-name>
<property-base>sim/model/livery</property-base>
<texture-prop>texture</texture-prop>
<texture>engine.png</texture>

</animation>

<model>
    <path>Aircraft/Q400/Models/interior.xml</path>
    <offsets>
      <x-m> 0.000 </x-m>
      <y-m> 0.000 </y-m>
      <z-m> 0.000 </z-m>
    </offsets>
  </model>

<model>
    <path>Aircraft/Q400/Models/cockpit.xml</path>
    <offsets>
      <x-m> 0.000 </x-m>
      <y-m> 0.000 </y-m>
      <z-m> 0.000 </z-m>
    </offsets>
  </model>

<model>
    <path>Aircraft/Q400/Models/panels.xml</path>
    <offsets>
      <x-m> 0.000 </x-m>
      <y-m> 0.000 </y-m>
      <z-m> 0.000 </z-m>
    </offsets>
  </model>


    <animation>
        <type>rotate</type>
        <object-name>Elevator</object-name>
        <property>controls/flight/elevator</property>
        <factor>15.0</factor>
        <center>
            <x-m>17.282</x-m>
            <y-m>0</y-m>
            <z-m>7.457</z-m>
        </center>
        <axis>
            <x>0</x>
            <y>1</y>
            <z>0</z>
        </axis>
    </animation>

    <animation>
        <type>rotate</type>
        <object-name>rudder</object-name>
        <property>controls/flight/rudder</property>
        <factor>15.0</factor>
        <center>
            <x-m>16.918</x-m>
            <y-m>0</y-m>
            <z-m>5.354</z-m>
        </center>
        <axis>
            <x>0.324</x>
            <y>0</y>
            <z>0.946</z>
        </axis>
    </animation>

    <animation>
        <type>rotate</type>
        <object-name>R.flap</object-name>
	  <object-name>rear-flap-rail</object-name>
        <property>surface-positions/flap-pos-norm</property>
        <factor>20.0</factor>
        <center>
            <x-m>-0.24</x-m>
            <y-m>7.31</y-m>
            <z-m>3.54</z-m>
        </center>
        <axis>
            <x>0</x>
            <y>0.999</y>
            <z>0.053</z>
        </axis>
    </animation>

    <animation>
        <type>rotate</type>
        <object-name>R.aileron</object-name>
        <property>controls/flight/aileron</property>
        <factor>-20.0</factor>
        <center>
            <x-m>0.96</x-m>
            <y-m>2.33</y-m>
            <z-m>3.49</z-m>
        </center>
        <axis>
            <x>0</x>
            <y>0.999</y>
            <z>0.053</z>
        </axis>
    </animation>

    <animation>
        <type>rotate</type>
        <object-name>L.flap</object-name>
	  <object-name>rear-flap-rail</object-name>
        <property>surface-positions/flap-pos-norm</property>
        <factor>-20.0</factor>
        <center>
            <x-m>0.24</x-m>
            <y-m>-7.31</y-m>
            <z-m>3.54</z-m>
        </center>
        <axis>
            <x>0</x>
            <y>-0.999</y>
            <z>0.053</z>
        </axis>
    </animation>

    <animation>
        <type>rotate</type>
        <object-name>L.aileron</object-name>
        <property>controls/flight/aileron</property>
        <factor>-20.0</factor>
        <center>
            <x-m>0.96</x-m>
            <y-m>-2.33</y-m>
            <z-m>3.49</z-m>
        </center>
        <axis>
            <x>0</x>
            <y>-0.999</y>
            <z>0.053</z>
        </axis>
    </animation>


<!-- Props -->

    <animation>
        <type>select</type>
        <object-name>propL</object-name>
        <condition>
            <less-than> 
            <property>engines/engine[0]/n2</property>
            <value>50.001</value>
            </less-than>
        </condition> 
    </animation>

    <animation>
        <type>select</type>
        <object-name>propdiscL</object-name>
        <condition>
            <greater-than> 
            <property>engines/engine[0]/n2</property>
            <value>50.000</value>
            </greater-than>
        </condition> 
    </animation>


<animation>
        <type>spin</type>
        <object-name>propdiscL</object-name>
        <object-name>propL</object-name>
        <property>engines/engine[0]/n2</property>
        <factor>80.0</factor>
        <center>
            <x-m>-3.74783</x-m>
            <y-m>-4.37881</y-m>
            <z-m>3.2705</z-m>
        </center>
        <axis>
            <x>1</x>
            <y>0</y>
            <z>0</z>
        </axis>
    </animation>

<animation>
        <type>select</type>
        <object-name>R.Prop</object-name>
        <condition>
            <less-than> 
            <property>engines/engine[1]/n2</property>
            <value>50.001</value>
            </less-than>
        </condition> 
    </animation>

    <animation>
        <type>select</type>
        <object-name>Rprop.disk</object-name>
        <condition>
            <greater-than> 
            <property>engines/engine[1]/n2</property>
            <value>50.000</value>
            </greater-than>
        </condition> 
    </animation>

 <animation>
        <type>spin</type>
        <object-name>Rprop.disk</object-name>
        <property>engines/engine[1]/n2</property>
        <factor>80.0</factor>
        <center>
            <x-m>3.59</x-m>
            <y-m>3.98</y-m>
            <z-m>2.95</z-m>
        </center>
        <axis>
            <x>1</x>
            <y>0</y>
            <z>0</z>
        </axis>
    </animation>

   

    <animation>
        <type>spin</type>
        <object-name>R.Prop</object-name>
        <property>engines/engine[1]/n2</property>
        <factor>80.0</factor>
        <center>
            <x-m>3.59</x-m>
            <y-m>3.98</y-m>
            <z-m>2.95</z-m>
        </center>
        <axis>
            <x>1</x>
            <y>0</y>
            <z>0</z>
        </axis>
    </animation>
<animation>
        <type>spin</type>
        <object-name>Rspinner</object-name>
        <property>engines/engine[1]/n2</property>
        <factor>15.0</factor>
        <center>
            <x-m>3.59</x-m>
            <y-m>3.98</y-m>
            <z-m>2.95</z-m>
        </center>
        <axis>
            <x>1</x>
            <y>0</y>
            <z>0</z>
        </axis>
    </animation>

<animation>
        <type>spin</type>
        <object-name>Lspinner</object-name>
        <property>engines/engine[1]/n2</property>
        <factor>15.0</factor>
        <center>
            <x-m>3.59</x-m>
            <y-m>-3.9764</y-m>
            <z-m>2.9082</z-m>
        </center>
        <axis>
            <x>1</x>
            <y>0</y>
            <z>0</z>
        </axis>
    </animation>



<!-- panel goes here-->

    <animation>
        <type>rotate</type>
        <object-name>LHthrottle</object-name>
        <property>controls/engines/engine[0]/throttle</property>
        <factor>50.0</factor>
        <center>
            <x-m>-11.1299</x-m>
            <y-m>0.0174</y-m>
            <z-m>1.9997</z-m>
        </center>
        <axis>
            <x>0</x>
            <y>-1</y>
            <z>0</z>
        </axis>
    </animation>

    <animation>
        <type>rotate</type>
        <object-name>RHthrottle</object-name>
        <property>controls/engines/engine[1]/throttle</property>
        <factor>50.0</factor>
        <center>
            <x-m>-11.1299</x-m>
            <y-m>0.0277</y-m>
            <z-m>1.9997</z-m>
        </center>
        <axis>
            <x>0</x>
            <y>-1</y>
            <z>0</z>
        </axis>
    </animation>

<animation>
        <type>rotate</type>
        <object-name>flaplever</object-name>
	<property>surface-positions/flap-pos-norm</property>
        <factor>40.0</factor>
        <center>
            <x-m>-11.1066</x-m>
            <y-m>0.1514</y-m>
            <z-m>1.9997</z-m>
        </center>
        <axis>
            <x>0</x>
            <y>1</y>
            <z>0</z>
        </axis>
    </animation>
 <animation>
        <type>rotate</type>
        <object-name>brake</object-name>
        <property>controls/gear/brake-parking</property>
        <factor>50</factor>
        <center>
            <x-m>-11.1299</x-m>
            <y-m>-0.0905</y-m>
            <z-m>1.9997</z-m>
        </center>
        <axis>
            <x>0</x>
            <y>1</y>
            <z>0</z>
        </axis>
    </animation>
<animation>
        <type>pick</type>
        <object-name>brake</object-name>
        <action>
            <button>0</button>
            <repeatable>true</repeatable>
            <interval-sec>0.5</interval-sec>
            <binding>
            <command>property-toggle</command>
            <property>controls/gear/brake-parking</property>
            </binding>
        </action>
    </animation>

    
<!-- Gear Animations -->
<animation>
<type>rotate</type>
  <object-name>FLG.doorL</object-name>
  <property>gear/gear[0]/position-norm</property>
      <interpolation> 
        <entry>
          <ind>1</ind>
          <dep>90</dep>
        </entry>
        <entry>
          <ind>0.2</ind>
          <dep>90</dep>
        </entry>
		<entry>
          <ind>0</ind>
          <dep>0</dep>
        </entry>
      </interpolation>
  <center>
   <x-m>-12.439</x-m>
   <y-m>-0.1549</y-m>
   <z-m>1.0213</z-m>
  </center>
  <axis>
   <x>-1.0</x>
   <y>0.0</y>
   <z>0.0</z>
  </axis>
 </animation>

<animation>
<type>rotate</type>
  <object-name>FLG.doorR</object-name>
  <property>gear/gear[0]/position-norm</property>
      <interpolation> 
        <entry>
          <ind>1</ind>
          <dep>90</dep>
        </entry>
        <entry>
          <ind>0.2</ind>
          <dep>90</dep>
        </entry>
		<entry>
          <ind>0</ind>
          <dep>0</dep>
        </entry>
      </interpolation>
  <center>
   <x-m>-12.439</x-m>
   <y-m>0.1549</y-m>
   <z-m>1.0213</z-m>
  </center>
  <axis>
   <x>1.0</x>
   <y>0.0</y>
   <z>0.0</z>
  </axis>
 </animation>



<animation>
 <type>rotate</type>
 <object-name>frontLG</object-name>
 <object-name>frontLGwheels</object-name>
<object-name>frontLG-gas-strut</object-name>
<object-name>frontLG-bottom-strut</object-name>
<object-name>frontLG-oleo</object-name>
<object-name>frontLG-rear-strut</object-name>
<object-name>frontLG-top-strut</object-name>
 <property>/gear/gear[0]/position-norm</property>
 <factor>120</factor>
 <offset-deg>-120</offset-deg>
 <min>90</min>
 <max>0</max>
 <center>
  <x-m>-11.953</x-m>
  <y-m>0.0</y-m>
  <z-m>1.217</z-m>
 </center>
 <axis>
  <x>0</x>
  <y>1</y>
  <z>0</z>
 </axis>
</animation>

<animation>
 <type>rotate</type>
 <object-name>frontLG</object-name>
 <object-name>frontLGwheels</object-name>
 <property>/gear/gear[0]/position-norm</property>
 <factor>90</factor>
 <offset-deg>-90</offset-deg>
 <min>90</min>
 <max>0</max>
 <center>
  <x-m>-12.1082</x-m>
  <y-m>0.0</y-m>
  <z-m>0.9077</z-m>
 </center>
 <axis>
  <x>0</x>
  <y>1</y>
  <z>0</z>
 </axis>
</animation>

<animation>
  <type>rotate</type>
  <object-name>LLG.door</object-name>
  <property>gear/gear[0]/position-norm</property>
      <interpolation> 
        <entry>
          <ind>1</ind>
          <dep>90</dep>
        </entry>
        <entry>
          <ind>0.2</ind>
          <dep>90</dep>
        </entry>
		<entry>
          <ind>0</ind>
          <dep>0</dep>
        </entry>
      </interpolation>
  <center>
   <x-m>0.16</x-m>
   <y-m>-4.32</y-m>
   <z-m>2.17</z-m>
  </center>
  <axis>
   <x>-1.0</x>
   <y>0.0</y>
   <z>0.0</z>
  </axis>
 </animation>


<animation>
 <type>rotate</type>
 <object-name>LLG</object-name>
<object-name>LLG.wheels</object-name>
<object-name>LLG.rear.strut</object-name>
 <property>/gear/gear[0]/position-norm</property>
 <factor>70</factor>
 <offset-deg>-70</offset-deg>
 <min>70</min>
 <max>0</max>
 <center>
  <x-m>-1.21</x-m>
  <y-m>-3.98</y-m>
  <z-m>2.33</z-m>
 </center>
 <axis>
  <x>0</x>
  <y>1</y>
  <z>0</z>
 </axis>
</animation>

<animation>
 <type>rotate</type>
 <object-name>LLG.rear.strut</object-name>
 <property>/gear/gear[0]/position-norm</property>
 <factor>14</factor>
 <offset-deg>-14</offset-deg>
 <min>14</min>
 <max>0</max>
 <center>
  <x-m>-0.1448</x-m>
  <y-m>-3.9998</y-m>
  <z-m>1.1511</z-m>
 </center>
 <axis>
  <x>0</x>
  <y>1</y>
  <z>0</z>
 </axis>
</animation>


<animation>
  <type>rotate</type>
  <object-name>RLG.door</object-name>
  <property>gear/gear[0]/position-norm</property>
      <interpolation> 
        <entry>
          <ind>1</ind>
          <dep>90</dep>
        </entry>
        <entry>
          <ind>0.2</ind>
          <dep>90</dep>
        </entry>
		<entry>
          <ind>0</ind>
          <dep>0</dep>
        </entry>
      </interpolation>
  <center>
   <x-m>0.16</x-m>
   <y-m>4.32</y-m>
   <z-m>2.17</z-m>
  </center>
  <axis>
   <x>1.0</x>
   <y>0.0</y>
   <z>0.0</z>
  </axis>
 </animation>


<animation>
 <type>rotate</type>
 <object-name>RLG</object-name>
<object-name>RLG.wheels</object-name>
<object-name>RLG.rear.strut</object-name>
 <property>/gear/gear[0]/position-norm</property>
 <factor>70</factor>
 <offset-deg>-70</offset-deg>
 <min>70</min>
 <max>0</max>
 <center>
  <x-m>-1.21</x-m>
  <y-m>3.98</y-m>
  <z-m>2.33</z-m>
 </center>
 <axis>
  <x>0</x>
  <y>1</y>
  <z>0</z>
 </axis>
</animation>

<animation>
 <type>rotate</type>
 <object-name>RLG.rear.strut</object-name>
 <property>/gear/gear[0]/position-norm</property>
 <factor>14</factor>
 <offset-deg>-14</offset-deg>
 <min>14</min>
 <max>0</max>
 <center>
  <x-m>-0.1448</x-m>
  <y-m>3.9998</y-m>
  <z-m>1.1511</z-m>
 </center>
 <axis>
  <x>0</x>
  <y>1</y>
  <z>0</z>
 </axis>
</animation>


  <animation>
    <type>rotate</type>
    <property>gear/gear[0]/steering-norm</property>
    <object-name>frontLG</object-name>
 <object-name>frontLGwheels</object-name>
    <factor>-30</factor>
    <center>
      <x-m>-11.953</x-m>
    </center>
    <axis>
      <z>1</z>
    </axis>
    <!-- The nosewheel steering has a microswitch to disable it
             once the nosewheel has left the ground -->
    <condition>
      <equals>
        <property>gear/gear[0]/wow</property>
        <value>true</value>
      </equals>
    </condition>

  </animation>


  <animation>
    <type>translate</type>
    <object-name>frontLGwheels</object-name>
    <property>gear/gear[0]/compression-norm</property>
    <factor>0.2</factor>
    <axis>
      <x>0</x>
      <y>0</y>
      <z>1</z>
    </axis>
  </animation>


  <!-- Nose gear Rolling -->
  <!-- 1ft radius * pi * 2  = 6.28 ft circumference -->
  <animation>
    <type>spin</type>
    <object-name>frontLGwheels</object-name>
    <property>gear/gear[1]/rollspeed-ms</property>
        <factor>10</factor>
    <center>
      <x-m>-11.9353</x-m>
      <z-m>0.2539</z-m>
    </center>
    <axis>
      <y>-1</y>
    </axis>
  </animation>

<animation>
    <type>spin</type>
    <object-name>RLG.wheels</object-name>
    <property>gear/gear[1]/rollspeed-ms</property>
        <factor>10</factor>
    <center>
      <x-m>0.0363</x-m>
      <z-m>0.4024</z-m>
	<y-m>3.98</y-m>
    </center>
    <axis>
      <y>-1</y>
    </axis>
  </animation>

<animation>
    <type>spin</type>
    <object-name>LLG.wheels</object-name>
    <property>gear/gear[1]/rollspeed-ms</property>
        <factor>10</factor>
    <center>
      <x-m>0.0396</x-m>
      <z-m>0.4033</z-m>
	<y-m>-3.98</y-m>
    </center>
    <axis>
      <y>-1</y>
    </axis>
  </animation>


<!-- hotspots -->

    <animation>
        <type>pick</type>
        <object-name>Lfuel.off</object-name>
        <action>
            <button>0</button>
            <repeatable>false</repeatable>
            <binding>
            <command>property-toggle</command>
            <property>controls/engines/engine[0]/cutoff</property>
        </binding>
        </action>
    </animation>

    <animation>
        <type>pick</type>
        <object-name>Rfuel.off</object-name>
        <action>
            <button>0</button>
            <repeatable>false</repeatable>
            <binding>
            <command>property-toggle</command>
            <property>controls/engines/engine[1]/cutoff</property>
        </binding>
        </action>
    </animation>


<!-- Instruments  will go here -->
    <animation>
        <type>rotate</type>
	  <object-name>cabindoor</object-name>
	  <object-name>step</object-name>
        <property>controls/doors/cabin-door-pos-norm</property>
	<interpolation> 
        <entry>
          <ind>0</ind>
          <dep>0</dep>
        </entry>
      <entry>
          <ind>0.1</ind>
          <dep>5</dep>
        </entry>
	<entry>
          <ind>0.5</ind>
          <dep>25</dep>
        </entry>
	<entry>
          <ind>0.9</ind>
          <dep>120</dep>
        </entry>
	<entry>
          <ind>1</ind>
          <dep>130</dep>
        </entry>
      </interpolation>

        <center>
            <x-m>-8.9991</x-m>
            <y-m>-0.9285</y-m>
            <z-m>1.2850</z-m>
        </center>

<axis>
            <x>1</x>
            <y>0</y>
            <z>0</z>
        </axis>
</animation>

<!-- Yokes -->

<model>
<path>Aircraft/Q400/Models/panels/yoke/yoke.xml</path>
<name>PilotYoke</name>     
<offsets>
<x-m>0</x-m>
<y-m>0</y-m>
<z-m>0</z-m>       
</offsets>
</model>

<model>
<path>Aircraft/Q400/Models/panels/yoke/yoke1.xml</path>
<name>C0PilotYoke</name>     
<offsets>
<x-m>0</x-m>
<y-m>0</y-m>
<z-m>0</z-m>       
</offsets>
</model>

<!-- LIGHTS -->

<model>
<path>Aircraft/Q400/Models/lights/GreenLight.xml</path>
<name>Greenlight</name>     
<offsets>
<x-m>-0.155666</x-m>
<y-m>13.004</y-m>
<z-m>3.8568</z-m>       
</offsets>
</model>

<model>
<path>Aircraft/Q400/Models/lights/RedLight.xml</path>
<name>Redlight</name>     
<offsets>
<x-m>-0.155666</x-m>
<y-m>-13.004</y-m>
<z-m>3.8568</z-m>       
</offsets>
</model>


<model>
<path>Aircraft/Q400/Models/lights/beacon.xml</path>
<name>flashtop</name>     
<offsets>
<x-m>15.3631</x-m>
<y-m>0.000</y-m>
<z-m>7.4286</z-m>   
</offsets>
</model>


<model>
<path>Aircraft/Q400/Models/lights/strobe.xml</path>
<name>strobeRHW</name>     
<offsets>
<x-m>0.4488</x-m>
<y-m>12.9876</y-m>
<z-m>3.8748</z-m>   
</offsets>
</model>

<model>
<path>Aircraft/Q400/Models/lights/strobe.xml</path>
<name>strobeLHW</name>     
<offsets>
<x-m>0.4488</x-m>
<y-m>-12.9876</y-m>
<z-m>3.8748</z-m>   
</offsets>
</model>

<model>
<path>Aircraft/Q400/Models/lights/strobe.xml</path>
<name>strobelower</name>     
<offsets>
<x-m>-3.4541</x-m>
<y-m>0</y-m>
<z-m>1.0133</z-m>   
</offsets>
</model>




</PropertyList>
